topsis/102003156.py
topsis/__init__.py
Topsis_Ravinshu_102003156-1.1.0.dist-info/LICENSE
Topsis_Ravinshu_102003156-1.1.0.dist-info/METADATA
Topsis_Ravinshu_102003156-1.1.0.dist-info/WHEEL
Topsis_Ravinshu_102003156-1.1.0.dist-info/entry_points.txt
Topsis_Ravinshu_102003156-1.1.0.dist-info/top_level.txt
Topsis_Ravinshu_102003156-1.1.0.dist-info/RECORD
