Metadata-Version: 2.1
Name: Topsis-Ravinshu-102003156
Version: 1.1.0
Summary: A convenient python package for Topsis rank and score calculation for a given dataset, weights and impacts
Author: Ravinshu Kushwaha
Author-email: rv.kushwaha01@gmail.com
License: MIT
Keywords: python,TOPSIS,MCDM,MCDA,statistics,prescriptive analytics,cli
Classifier: Development Status :: 3 - Alpha
Classifier: Intended Audience :: Developers
Classifier: Topic :: Software Development :: Build Tools
Classifier: License :: OSI Approved :: MIT License
Classifier: Programming Language :: Python :: 3
Classifier: Programming Language :: Python :: 3.4
Classifier: Programming Language :: Python :: 3.5
Classifier: Programming Language :: Python :: 3.6
License-File: LICENSE
Requires-Dist: pandas
Requires-Dist: numpy
